pynetsnmp/CONSTANTS.py
pynetsnmp/SnmpSession.py
pynetsnmp/__init__.py
pynetsnmp/genconstants.py
pynetsnmp/netsnmp.py
pynetsnmp/tableretriever.py
pynetsnmp/twistedsnmp.py
pynetsnmp_2-0.1.10.dist-info/LICENSE.txt
pynetsnmp_2-0.1.10.dist-info/METADATA
pynetsnmp_2-0.1.10.dist-info/WHEEL
pynetsnmp_2-0.1.10.dist-info/top_level.txt
pynetsnmp_2-0.1.10.dist-info/RECORD
