Metadata-Version: 2.1
Name: pynetsnmp-2
Version: 0.1.10
Summary: ctypes wrapper for net-snmp
Home-page: https://github.com/Uninett/pynetsnmp
Author: Zenoss
Author-email: support@zenoss.com
Maintainer: Morten Brekkevold
Maintainer-email: morten.brekkevold@sikt.no
License: GPLv2+
Keywords: snmp,twisted,pynetsnmp,netsnmp
Platform: any
Classifier: Development Status :: 5 - Production/Stable
Classifier: Intended Audience :: Developers
Classifier: License :: OSI Approved :: GNU General Public License v2 or later (GPLv2+)
Classifier: Programming Language :: Python :: 3
Classifier: Programming Language :: Python :: 3.7
Classifier: Programming Language :: Python :: 3.8
Classifier: Programming Language :: Python :: 3.9
Classifier: Topic :: System :: Monitoring
Classifier: Topic :: System :: Networking :: Monitoring
License-File: LICENSE.txt
Requires-Dist: setuptools
Requires-Dist: ipaddr
Requires-Dist: Twisted
Requires-Dist: six
